dkconfig/__init__.py
dkconfig/_version.py
dkconfig/dkconfig.py
dkconfig-0.2.2.dist-info/LICENSE
dkconfig-0.2.2.dist-info/METADATA
dkconfig-0.2.2.dist-info/WHEEL
dkconfig-0.2.2.dist-info/entry_points.txt
dkconfig-0.2.2.dist-info/top_level.txt
dkconfig-0.2.2.dist-info/RECORD
