Metadata-Version: 2.1
Name: dkconfig
Version: 0.2.2
Summary: dkconfig - command line access to ConfigParser
Home-page: https://github.com/datakortet/dkconfig
License: MIT
Platform: UNKNOWN
Classifier: Development Status :: 4 - Beta
Classifier: Intended Audience :: Developers
Classifier: License :: OSI Approved :: MIT License
Classifier: Programming Language :: Python
Classifier: Programming Language :: Python :: 3
Classifier: Topic :: Software Development :: Libraries
License-File: LICENSE
Requires-Dist: lockfile (>=0.10.2)
